skstats/__init__.py
skstats/version.py
skstats/hypotests/__init__.py
skstats/hypotests/exceptions.py
skstats/hypotests/parameters.py
skstats/hypotests/calculators/__init__.py
skstats/hypotests/calculators/asymptotic_calculator.py
skstats/hypotests/calculators/basecalculator.py
skstats/hypotests/core/__init__.py
skstats/hypotests/core/basetest.py
skstats/hypotests/core/confidence_interval.py
skstats/hypotests/core/discovery.py
skstats/hypotests/core/upperlimit.py
skstats/hypotests/fitutils/__init__.py
skstats/hypotests/fitutils/api_check.py
skstats/hypotests/fitutils/utils.py
skstats/modeling/__init__.py
skstats/modeling/bayesian_blocks.py
tests/__init__.py
tests/conftest.py
tests/modeling/__init__.py
tests/modeling/test_bayesianblocks.py
scikit_stats-0.1.2.dist-info/METADATA
scikit_stats-0.1.2.dist-info/WHEEL
scikit_stats-0.1.2.dist-info/top_level.txt
scikit_stats-0.1.2.dist-info/RECORD
