Metadata-Version: 2.1
Name: scikit-stats
Version: 0.1.2
Summary: statistics tools and utilities
Home-page: https://github.com/scikit-hep/scikit-stats
Author: Matthieu Marinangeli
Author-email: matthieu.marinangeli@cern.ch
Maintainer: The Scikit-HEP admins
Maintainer-email: scikit-hep-admins@googlegroups.com
License: BSD 3-Clause License
Keywords: HEP,statistics
Platform: Any
Classifier: Topic :: Scientific/Engineering
Classifier: Intended Audience :: Science/Research
Classifier: Intended Audience :: Developers
Classifier: Operating System :: OS Independent
Classifier: License :: OSI Approved :: BSD License
Classifier: Programming Language :: Python
Classifier: Programming Language :: Python :: 3
Classifier: Programming Language :: Python :: 3.6
Classifier: Programming Language :: Python :: 3.7
Classifier: Development Status :: 4 - Beta
Requires-Python: !=2.*, >=3.6
Requires-Dist: scipy
Requires-Dist: numpy
Requires-Dist: pandas
